lsh/__init__.py
lsh/hash_functions.py
lsh_fast-0.1.0.dist-info/LICENSE
lsh_fast-0.1.0.dist-info/METADATA
lsh_fast-0.1.0.dist-info/WHEEL
lsh_fast-0.1.0.dist-info/top_level.txt
lsh_fast-0.1.0.dist-info/RECORD
